mlpytools/__init__.py
mlpytools/__main__.py
mlpytools/linear_algebra/__init__.py
mlpytools/linear_algebra/matrix.py
mlpytools-0.1.0.dist-info/LICENSE
mlpytools-0.1.0.dist-info/METADATA
mlpytools-0.1.0.dist-info/WHEEL
mlpytools-0.1.0.dist-info/entry_points.txt
mlpytools-0.1.0.dist-info/RECORD
