Metadata-Version: 2.1
Name: mlpytools
Version: 0.1.0
Summary: 
License: MIT
Author: Miller
Author-email: miltonycchow@gmail.com
Requires-Python: >=3.10,<3.11
Classifier: License :: OSI Approved :: MIT License
Classifier: Programming Language :: Python :: 3
Classifier: Programming Language :: Python :: 3.10
Requires-Dist: numpy (>=2.1.3,<3.0.0)
Requires-Dist: pandas (>=2.2.3,<3.0.0)
